<annotation>
	<folder>Train</folder>
	<filename>533.jpg</filename>
	<path>C:/Users/Buse/Desktop/Train/533.jpg</path>
	<source>
		<database>Unknown</database>
	</source>
	<size>
		<width>640</width>
		<height>426</height>
		<depth>3</depth>
	</size>
	<segmented>0</segmented>
	<object>
		<name>green light</name>
		<pose>Unspecified</pose>
		<truncated>0</truncated>
		<difficult>0</difficult>
		<bndbox>
			<xmin>130</xmin>
			<ymin>18</ymin>
			<xmax>172</xmax>
			<ymax>63</ymax>
		</bndbox>
	</object>
	<object>
		<name>speed limit 70</name>
		<pose>Unspecified</pose>
		<truncated>0</truncated>
		<difficult>0</difficult>
		<bndbox>
			<xmin>219</xmin>
			<ymin>16</ymin>
			<xmax>253</xmax>
			<ymax>45</ymax>
		</bndbox>
	</object>
	<object>
		<name>pedestrian crossing</name>
		<pose>Unspecified</pose>
		<truncated>0</truncated>
		<difficult>0</difficult>
		<bndbox>
			<xmin>464</xmin>
			<ymin>19</ymin>
			<xmax>506</xmax>
			<ymax>64</ymax>
		</bndbox>
	</object>
	<object>
		<name>stop sign</name>
		<pose>Unspecified</pose>
		<truncated>0</truncated>
		<difficult>0</difficult>
		<bndbox>
			<xmin>541</xmin>
			<ymin>28</ymin>
			<xmax>601</xmax>
			<ymax>92</ymax>
		</bndbox>
	</object>
</annotation>
