<annotation>
	<folder>Train</folder>
	<filename>636.jpg</filename>
	<path>C:/Users/Buse/Desktop/Train/636.jpg</path>
	<source>
		<database>Unknown</database>
	</source>
	<size>
		<width>640</width>
		<height>426</height>
		<depth>3</depth>
	</size>
	<segmented>0</segmented>
	<object>
		<name>speed limit 70</name>
		<pose>Unspecified</pose>
		<truncated>0</truncated>
		<difficult>0</difficult>
		<bndbox>
			<xmin>120</xmin>
			<ymin>18</ymin>
			<xmax>168</xmax>
			<ymax>62</ymax>
		</bndbox>
	</object>
	<object>
		<name>do not enter</name>
		<pose>Unspecified</pose>
		<truncated>0</truncated>
		<difficult>0</difficult>
		<bndbox>
			<xmin>236</xmin>
			<ymin>16</ymin>
			<xmax>261</xmax>
			<ymax>39</ymax>
		</bndbox>
	</object>
	<object>
		<name>green light</name>
		<pose>Unspecified</pose>
		<truncated>0</truncated>
		<difficult>0</difficult>
		<bndbox>
			<xmin>422</xmin>
			<ymin>21</ymin>
			<xmax>459</xmax>
			<ymax>51</ymax>
		</bndbox>
	</object>
	<object>
		<name>speed limit 50</name>
		<pose>Unspecified</pose>
		<truncated>0</truncated>
		<difficult>0</difficult>
		<bndbox>
			<xmin>465</xmin>
			<ymin>19</ymin>
			<xmax>513</xmax>
			<ymax>66</ymax>
		</bndbox>
	</object>
	<object>
		<name>red light</name>
		<pose>Unspecified</pose>
		<truncated>0</truncated>
		<difficult>0</difficult>
		<bndbox>
			<xmin>568</xmin>
			<ymin>39</ymin>
			<xmax>634</xmax>
			<ymax>109</ymax>
		</bndbox>
	</object>
</annotation>
