<annotation>
	<folder>Train</folder>
	<filename>892.jpg</filename>
	<path>C:/Users/Buse/Desktop/Train/892.jpg</path>
	<source>
		<database>Unknown</database>
	</source>
	<size>
		<width>640</width>
		<height>426</height>
		<depth>3</depth>
	</size>
	<segmented>0</segmented>
	<object>
		<name>speed limit 50</name>
		<pose>Unspecified</pose>
		<truncated>0</truncated>
		<difficult>0</difficult>
		<bndbox>
			<xmin>18</xmin>
			<ymin>31</ymin>
			<xmax>83</xmax>
			<ymax>97</ymax>
		</bndbox>
	</object>
	<object>
		<name>do not enter</name>
		<pose>Unspecified</pose>
		<truncated>0</truncated>
		<difficult>0</difficult>
		<bndbox>
			<xmin>149</xmin>
			<ymin>20</ymin>
			<xmax>189</xmax>
			<ymax>60</ymax>
		</bndbox>
	</object>
	<object>
		<name>speed limit 70</name>
		<pose>Unspecified</pose>
		<truncated>0</truncated>
		<difficult>0</difficult>
		<bndbox>
			<xmin>465</xmin>
			<ymin>20</ymin>
			<xmax>510</xmax>
			<ymax>67</ymax>
		</bndbox>
	</object>
	<object>
		<name>stop sign</name>
		<pose>Unspecified</pose>
		<truncated>0</truncated>
		<difficult>0</difficult>
		<bndbox>
			<xmin>538</xmin>
			<ymin>29</ymin>
			<xmax>598</xmax>
			<ymax>91</ymax>
		</bndbox>
	</object>
</annotation>
