<annotation>
	<folder>Train</folder>
	<filename>926.jpg</filename>
	<path>C:/Users/Buse/Desktop/Train/926.jpg</path>
	<source>
		<database>Unknown</database>
	</source>
	<size>
		<width>640</width>
		<height>426</height>
		<depth>3</depth>
	</size>
	<segmented>0</segmented>
	<object>
		<name>do not enter</name>
		<pose>Unspecified</pose>
		<truncated>0</truncated>
		<difficult>0</difficult>
		<bndbox>
			<xmin>25</xmin>
			<ymin>28</ymin>
			<xmax>89</xmax>
			<ymax>99</ymax>
		</bndbox>
	</object>
	<object>
		<name>pedestrian crossing</name>
		<pose>Unspecified</pose>
		<truncated>0</truncated>
		<difficult>0</difficult>
		<bndbox>
			<xmin>524</xmin>
			<ymin>22</ymin>
			<xmax>581</xmax>
			<ymax>88</ymax>
		</bndbox>
	</object>
</annotation>
