<annotation>
	<folder>7</folder>
	<filename>image16.jpg</filename>
	<path>C:/Users/Buse/Desktop/frames/7/image16.jpg</path>
	<source>
		<database>Unknown</database>
	</source>
	<size>
		<width>640</width>
		<height>426</height>
		<depth>3</depth>
	</size>
	<segmented>0</segmented>
	<object>
		<name>school crossing</name>
		<pose>Unspecified</pose>
		<truncated>0</truncated>
		<difficult>0</difficult>
		<bndbox>
			<xmin>112</xmin>
			<ymin>23</ymin>
			<xmax>146</xmax>
			<ymax>59</ymax>
		</bndbox>
	</object>
	<object>
		<name>speed limit 70</name>
		<pose>Unspecified</pose>
		<truncated>0</truncated>
		<difficult>0</difficult>
		<bndbox>
			<xmin>407</xmin>
			<ymin>9</ymin>
			<xmax>450</xmax>
			<ymax>51</ymax>
		</bndbox>
	</object>
	<object>
		<name>speed limit 50</name>
		<pose>Unspecified</pose>
		<truncated>0</truncated>
		<difficult>0</difficult>
		<bndbox>
			<xmin>481</xmin>
			<ymin>13</ymin>
			<xmax>541</xmax>
			<ymax>73</ymax>
		</bndbox>
	</object>
	<object>
		<name>green light</name>
		<pose>Unspecified</pose>
		<truncated>1</truncated>
		<difficult>0</difficult>
		<bndbox>
			<xmin>590</xmin>
			<ymin>29</ymin>
			<xmax>640</xmax>
			<ymax>117</ymax>
		</bndbox>
	</object>
</annotation>
